{
	"meta": {
		"cityName": "Berlin",
		"countryId": "germany",
		"geo": {
			"center": [
				13.430802944062751,
				52.51556243664122
			]
		},
		"id": "berlin",
		"name": "🇩🇪 Berlin, Germany",
		"url": "https://equalstreetnames-berlin.openstreetmap.de/",
		"update": "2025-12-02T05:17:42.178Z"
	},
	"statistics": [
		{
			"date": "2020-07-11T17:55:23Z",
			"values": {
				"F": 7,
				"M": 25,
				"FX": 0,
				"MX": 0,
				"X": 0,
				"+": 0,
				"?": 0,
				"-": 11371
			},
			"sources": null
		},
		{
			"date": "2021-03-21T16:56:58Z",
			"values": {
				"F": 373,
				"M": 3024,
				"FX": 1,
				"MX": 0,
				"X": 0,
				"+": 7,
				"?": 0,
				"-": 8007
			},
			"sources": null
		},
		{
			"date": "2021-03-25T03:14:11Z",
			"values": {
				"F": 373,
				"M": 3024,
				"FX": 1,
				"MX": 0,
				"X": 0,
				"NB": 0,
				"+": 7,
				"?": 0,
				"-": 8007
			},
			"sources": null
		},
		{
			"date": "2021-04-01T03:44:23Z",
			"values": {
				"F": 373,
				"M": 3023,
				"FX": 1,
				"MX": 0,
				"X": 0,
				"NB": 0,
				"+": 7,
				"?": 0,
				"-": 8011
			},
			"sources": null
		},
		{
			"date": "2021-04-08T03:30:10Z",
			"values": {
				"F": 373,
				"M": 3023,
				"FX": 1,
				"MX": 0,
				"X": 0,
				"NB": 0,
				"+": 7,
				"?": 0,
				"-": 8012
			},
			"sources": null
		},
		{
			"date": "2021-04-10T14:46:58Z",
			"values": {
				"F": 373,
				"M": 3023,
				"FX": 1,
				"MX": 0,
				"X": 0,
				"NB": 0,
				"+": 7,
				"?": 0,
				"-": 8011
			},
			"sources": null
		},
		{
			"date": "2021-04-15T02:51:19Z",
			"values": {
				"F": 373,
				"M": 3024,
				"FX": 1,
				"MX": 0,
				"X": 0,
				"NB": 0,
				"+": 7,
				"?": 0,
				"-": 8012
			},
			"sources": null
		},
		{
			"date": "2021-04-22T02:54:07Z",
			"values": {
				"F": 373,
				"M": 3025,
				"FX": 1,
				"MX": 0,
				"X": 0,
				"NB": 0,
				"+": 7,
				"?": 0,
				"-": 8012
			},
			"sources": {
				"wikidata": 9891,
				"config": 0,
				"event": 0,
				"-": 1527
			}
		},
		{
			"date": "2021-04-29T02:54:52Z",
			"values": {
				"F": 374,
				"M": 3025,
				"FX": 1,
				"MX": 0,
				"X": 0,
				"NB": 0,
				"+": 7,
				"?": 0,
				"-": 8013
			},
			"sources": {
				"wikidata": 9893,
				"config": 0,
				"event": 0,
				"-": 1527
			}
		},
		{
			"date": "2021-05-01T15:20:40Z",
			"values": {
				"F": 374,
				"M": 3032,
				"FX": 1,
				"MX": 0,
				"X": 0,
				"NB": 0,
				"+": 7,
				"?": 0,
				"-": 8007
			},
			"sources": {
				"wikidata": 9895,
				"config": 0,
				"event": 0,
				"-": 1526
			}
		},
		{
			"date": "2021-05-04T02:28:13Z",
			"values": {
				"F": 373,
				"M": 3032,
				"FX": 1,
				"MX": 0,
				"X": 0,
				"NB": 0,
				"+": 7,
				"?": 1,
				"-": 7911
			},
			"sources": {
				"wikidata": 9919,
				"config": 0,
				"event": 0,
				"-": 1406
			}
		},
		{
			"date": "2021-05-11T02:30:02Z",
			"values": {
				"F": 374,
				"M": 3030,
				"FX": 1,
				"MX": 0,
				"X": 0,
				"NB": 0,
				"+": 7,
				"?": 1,
				"-": 7914
			},
			"sources": {
				"wikidata": 9917,
				"csv": 0,
				"config": 0,
				"event": 0,
				"-": 1410
			}
		},
		{
			"date": "2022-11-02T13:11:06Z",
			"values": {
				"F": 377,
				"M": 3015,
				"FX": 1,
				"MX": 0,
				"X": 0,
				"NB": 0,
				"+": 7,
				"?": 1,
				"-": 7730
			},
			"sources": {
				"wikidata": 9647,
				"csv": 0,
				"config": 0,
				"-": 1484
			}
		},
		{
			"date": "2022-12-02T12:58:47Z",
			"values": {
				"F": 376,
				"M": 3012,
				"FX": 1,
				"MX": 2,
				"X": 0,
				"NB": 0,
				"+": 7,
				"?": 1,
				"-": 7737
			},
			"sources": {
				"wikidata": 9640,
				"csv": 0,
				"config": 0,
				"-": 1496
			}
		},
		{
			"date": "2023-01-02T13:16:12Z",
			"values": {
				"F": 375,
				"M": 3016,
				"FX": 1,
				"MX": 0,
				"X": 0,
				"NB": 0,
				"+": 7,
				"?": 1,
				"-": 7747
			},
			"sources": {
				"wikidata": 9631,
				"csv": 0,
				"config": 0,
				"-": 1516
			}
		},
		{
			"date": "2023-02-02T13:04:21Z",
			"values": {
				"F": 374,
				"M": 3015,
				"FX": 1,
				"MX": 0,
				"X": 0,
				"NB": 0,
				"+": 7,
				"?": 1,
				"-": 7743
			},
			"sources": {
				"wikidata": 9623,
				"csv": 0,
				"config": 0,
				"-": 1518
			}
		},
		{
			"date": "2023-03-02T13:22:53Z",
			"values": {
				"F": 378,
				"M": 3019,
				"FX": 1,
				"MX": 0,
				"X": 0,
				"NB": 0,
				"+": 7,
				"?": 1,
				"-": 7735
			},
			"sources": {
				"wikidata": 9631,
				"csv": 0,
				"config": 0,
				"-": 1510
			}
		},
		{
			"date": "2023-03-06T20:19:23Z",
			"values": {
				"F": 378,
				"M": 3018,
				"FX": 1,
				"MX": 0,
				"X": 0,
				"NB": 0,
				"+": 7,
				"?": 1,
				"-": 7737
			},
			"sources": {
				"wikidata": 9631,
				"csv": 0,
				"config": 0,
				"-": 1511
			}
		},
		{
			"date": "2023-04-02T12:58:32Z",
			"values": {
				"F": 373,
				"M": 3018,
				"FX": 1,
				"MX": 0,
				"X": 0,
				"NB": 0,
				"+": 7,
				"?": 1,
				"-": 7696
			},
			"sources": {
				"wikidata": 9596,
				"csv": 0,
				"config": 0,
				"-": 1500
			}
		},
		{
			"date": "2023-05-02T13:25:07Z",
			"values": {
				"F": 373,
				"M": 3018,
				"FX": 1,
				"MX": 0,
				"X": 0,
				"NB": 0,
				"+": 7,
				"?": 1,
				"-": 7691
			},
			"sources": {
				"wikidata": 9594,
				"csv": 0,
				"config": 0,
				"-": 1497
			}
		},
		{
			"date": "2023-06-02T13:08:43Z",
			"values": {
				"F": 373,
				"M": 3019,
				"FX": 1,
				"MX": 0,
				"X": 0,
				"NB": 0,
				"+": 7,
				"?": 1,
				"-": 7699
			},
			"sources": {
				"wikidata": 9597,
				"csv": 0,
				"config": 0,
				"-": 1503
			}
		},
		{
			"date": "2023-07-02T13:09:26Z",
			"values": {
				"F": 373,
				"M": 3017,
				"FX": 1,
				"MX": 0,
				"X": 0,
				"NB": 0,
				"+": 7,
				"?": 1,
				"-": 7711
			},
			"sources": {
				"wikidata": 9596,
				"csv": 0,
				"config": 0,
				"-": 1514
			}
		},
		{
			"date": "2023-08-02T13:12:25Z",
			"values": {
				"F": 375,
				"M": 3014,
				"FX": 1,
				"MX": 0,
				"X": 0,
				"NB": 0,
				"+": 7,
				"?": 1,
				"-": 7696
			},
			"sources": {
				"wikidata": 9581,
				"csv": 0,
				"config": 0,
				"-": 1513
			}
		},
		{
			"date": "2023-09-02T13:04:09Z",
			"values": {
				"F": 374,
				"M": 3014,
				"FX": 1,
				"MX": 0,
				"X": 0,
				"NB": 1,
				"+": 7,
				"?": 1,
				"-": 7690
			},
			"sources": {
				"wikidata": 9581,
				"csv": 0,
				"config": 0,
				"-": 1507
			}
		},
		{
			"date": "2023-10-02T13:10:47Z",
			"values": {
				"F": 375,
				"M": 3014,
				"FX": 1,
				"MX": 0,
				"X": 0,
				"NB": 0,
				"+": 7,
				"?": 1,
				"-": 7695
			},
			"sources": {
				"wikidata": 9581,
				"csv": 0,
				"config": 0,
				"-": 1512
			}
		},
		{
			"date": "2023-11-02T13:05:29Z",
			"values": {
				"F": 377,
				"M": 3013,
				"FX": 1,
				"MX": 0,
				"X": 0,
				"NB": 0,
				"+": 7,
				"?": 1,
				"-": 7695
			},
			"sources": {
				"wikidata": 9582,
				"csv": 0,
				"config": 0,
				"-": 1512
			}
		},
		{
			"date": "2023-12-02T12:58:42Z",
			"values": {
				"F": 378,
				"M": 3013,
				"FX": 1,
				"MX": 0,
				"X": 0,
				"NB": 0,
				"+": 7,
				"?": 1,
				"-": 7695
			},
			"sources": {
				"wikidata": 9581,
				"csv": 0,
				"config": 0,
				"-": 1514
			}
		},
		{
			"date": "2024-03-19T21:34:44Z",
			"values": {
				"F": 377,
				"M": 3007,
				"FX": 1,
				"MX": 0,
				"X": 0,
				"NB": 0,
				"+": 7,
				"?": 3,
				"-": 7695
			},
			"sources": {
				"wikidata": 9569,
				"csv": 0,
				"config": 0,
				"-": 1521
			}
		},
		{
			"date": "2024-04-02T12:53:19Z",
			"values": {
				"F": 377,
				"M": 3006,
				"FX": 1,
				"MX": 0,
				"X": 0,
				"NB": 0,
				"+": 7,
				"?": 3,
				"-": 7695
			},
			"sources": {
				"wikidata": 9569,
				"csv": 0,
				"config": 0,
				"-": 1520
			}
		},
		{
			"date": "2024-05-02T12:58:14Z",
			"values": {
				"F": 380,
				"M": 3004,
				"FX": 1,
				"MX": 0,
				"X": 0,
				"NB": 0,
				"+": 7,
				"?": 2,
				"-": 7703
			},
			"sources": {
				"wikidata": 9571,
				"csv": 0,
				"config": 0,
				"-": 1526
			}
		},
		{
			"date": "2024-06-02T13:02:55Z",
			"values": {
				"F": 379,
				"M": 3004,
				"FX": 1,
				"MX": 0,
				"X": 0,
				"NB": 0,
				"+": 7,
				"?": 2,
				"-": 7705
			},
			"sources": {
				"wikidata": 9571,
				"csv": 0,
				"config": 0,
				"-": 1527
			}
		},
		{
			"date": "2025-01-02T12:57:06Z",
			"values": {
				"F": 379,
				"M": 2996,
				"FX": 1,
				"MX": 0,
				"X": 0,
				"NB": 0,
				"+": 7,
				"?": 2,
				"-": 7696
			},
			"sources": {
				"wikidata": 9547,
				"csv": 0,
				"config": 0,
				"-": 1534
			}
		},
		{
			"date": "2025-02-02T12:41:40Z",
			"values": {
				"F": 379,
				"M": 2996,
				"FX": 1,
				"MX": 0,
				"X": 0,
				"NB": 0,
				"+": 7,
				"?": 2,
				"-": 7707
			},
			"sources": {
				"wikidata": 9552,
				"csv": 0,
				"config": 0,
				"-": 1540
			}
		},
		{
			"date": "2025-03-02T12:50:50Z",
			"values": {
				"F": 379,
				"M": 2995,
				"FX": 1,
				"MX": 0,
				"X": 0,
				"NB": 0,
				"+": 7,
				"?": 2,
				"-": 7702
			},
			"sources": {
				"wikidata": 9545,
				"csv": 0,
				"config": 0,
				"-": 1541
			}
		},
		{
			"date": "2025-04-02T12:49:17Z",
			"values": {
				"F": 379,
				"M": 2992,
				"FX": 1,
				"MX": 0,
				"X": 0,
				"NB": 0,
				"+": 7,
				"?": 2,
				"-": 7705
			},
			"sources": {
				"wikidata": 9538,
				"csv": 0,
				"config": 0,
				"-": 1548
			}
		},
		{
			"date": "2025-05-02T12:56:31Z",
			"values": {
				"F": 379,
				"M": 2992,
				"FX": 1,
				"MX": 0,
				"X": 0,
				"NB": 0,
				"+": 7,
				"?": 2,
				"-": 7710
			},
			"sources": {
				"wikidata": 9537,
				"csv": 0,
				"config": 0,
				"-": 1554
			}
		},
		{
			"date": "2025-06-02T12:51:15Z",
			"values": {
				"F": 379,
				"M": 2992,
				"FX": 1,
				"MX": 0,
				"X": 0,
				"NB": 0,
				"+": 7,
				"?": 2,
				"-": 7715
			},
			"sources": {
				"wikidata": 9537,
				"csv": 0,
				"config": 0,
				"-": 1559
			}
		},
		{
			"date": "2025-07-02T13:06:30Z",
			"values": {
				"F": 379,
				"M": 2992,
				"FX": 1,
				"MX": 0,
				"X": 0,
				"NB": 0,
				"+": 7,
				"?": 2,
				"-": 7720
			},
			"sources": {
				"wikidata": 9538,
				"csv": 0,
				"config": 0,
				"-": 1563
			}
		},
		{
			"date": "2025-08-02T12:48:07Z",
			"values": {
				"F": 382,
				"M": 2992,
				"FX": 1,
				"MX": 0,
				"X": 0,
				"NB": 0,
				"+": 7,
				"?": 2,
				"-": 7721
			},
			"sources": {
				"wikidata": 9541,
				"csv": 0,
				"config": 0,
				"-": 1564
			}
		},
		{
			"date": "2025-09-02T12:59:40Z",
			"values": {
				"F": 383,
				"M": 2994,
				"FX": 1,
				"MX": 0,
				"X": 0,
				"NB": 0,
				"+": 7,
				"?": 2,
				"-": 7724
			},
			"sources": {
				"wikidata": 9544,
				"csv": 0,
				"config": 0,
				"-": 1567
			}
		},
		{
			"date": "2025-10-02T13:01:11Z",
			"values": {
				"F": 366,
				"M": 2950,
				"FX": 1,
				"MX": 0,
				"X": 0,
				"NB": 0,
				"+": 7,
				"?": 64,
				"-": 7728
			},
			"sources": {
				"wikidata": 9540,
				"csv": 0,
				"config": 0,
				"-": 1576
			}
		},
		{
			"date": "2025-11-02T12:46:47Z",
			"values": {
				"F": 367,
				"M": 2947,
				"FX": 1,
				"MX": 0,
				"X": 0,
				"NB": 0,
				"+": 7,
				"?": 64,
				"-": 7736
			},
			"sources": {
				"wikidata": 9537,
				"csv": 0,
				"config": 0,
				"-": 1585
			}
		}
	]
}